fair_test/__init__.py
fair_test/config.py
fair_test/fair_test.py
fair_test/fair_test_api.py
fair_test/fair_test_evaluation.py
fair_test/fair_test_logger.py
fair_test/metadata_harvester.py
fair_test/py.typed
fair_test-0.1.4.dist-info/METADATA
fair_test-0.1.4.dist-info/WHEEL
fair_test-0.1.4.dist-info/licenses/LICENSE.txt
fair_test-0.1.4.dist-info/RECORD
